<?xml version="1.0" encoding="UTF-8"?>
<beans xmlns="http://www.springframework.org/schema/beans"
    xmlns:xsi="http://www.w3.org/2001/XMLSchema-instance"
     xmlns:aop="http://www.springframework.org/schema/aop"
    xmlns:mvc="http://www.springframework.org/schema/mvc"
    xmlns:tx="http://www.springframework.org/schema/tx" xmlns:context="http://www.springframework.org/schema/context"
    xsi:schemaLocation="http://www.springframework.org/schema/beans
    http://www.springframework.org/schema/beans/spring-beans.xsd 
    http://www.springframework.org/schema/aop 
    http://www.springframework.org/schema/aop/spring-aop.xsd 
        http://www.springframework.org/schema/mvc 
        http://www.springframework.org/schema/mvc/spring-mvc.xsd
    http://www.springframework.org/schema/context
    http://www.springframework.org/schema/context/spring-context.xsd
    http://www.springframework.org/schema/tx
    http://www.springframework.org/schema/tx/spring-tx.xsd">
        
    <!-- Enabling all the spring mvc features -->
	<mvc:annotation-driven />
    
    	<!-- This is the package name where we keep out model/controller -->
	<context:component-scan	base-package="com.kuebiko.controller" />
	<context:component-scan	base-package="com.kuebiko.dao" />
	<context:component-scan	base-package="com.kuebiko.service" />
	
		
  <!-- the mvc resources tag does the magic -->
 <mvc:resources mapping="/img/**" location="/img/" />
	
	<!-- Hello I am using JSP -->
	<bean id="viewResolver"
		class="org.springframework.web.servlet.view.UrlBasedViewResolver">
		<property name="viewClass"
			value="org.springframework.web.servlet.view.JstlView" />
		<property name="prefix" value="/WEB-INF/pages/" />
		<property name="suffix" value=".jsp" />
	</bean>
	
	  <bean id="multipartResolver" class="org.springframework.web.multipart.support.StandardServletMultipartResolver"/>
	
	<bean id="pkdataSource"		class="org.springframework.jdbc.datasource.DriverManagerDataSource">
		<property name="driverClassName"
			value="com.mysql.jdbc.Driver" />
		<property name="url" value="jdbc:mysql://localhost:3306/movie_db" />
		<property name="username" value="root" />
		<property name="password" value="mysql@1234" />
	</bean>
	
	
	<!-- 
       Create a session factory
     -->
      <bean id="psessionFactory"   class="org.springframework.orm.hibernate5.LocalSessionFactoryBean">
        <property name="dataSource"      ref="pkdataSource"/>
        <property name="packagesToScan"  value="com.kuebiko.entity"/>
        <property name="hibernateProperties">
            <props>
            <!-- below will generate schema for you -->
                <prop key="hibernate.hbm2ddl.auto">update</prop>    
                                 <!-- below will generate database specific query -->
                   <prop key="hibernate.dialect">org.hibernate.dialect.MySQL5InnoDBDialect</prop>
                 <!-- Below will print the  --> 
                <prop key="hibernate.show_sql">true</prop>
            </props>
        </property>
    </bean>
    
        <bean id="transactionManager"    class="org.springframework.orm.hibernate5.HibernateTransactionManager">
                <property name="sessionFactory" ref="psessionFactory"/>
    </bean>
    
    <!-- enable the configuration of transactional behavior based on annotations -->
	<tx:annotation-driven transaction-manager="transactionManager" />
            
    </beans>    